{
  "generated_for": "2026-06-09",
  "window_days": 2,
  "accuracy": {
    "overall": {
      "graded": 3,
      "accuracy": 0.3333,
      "brier": 0.2971
    },
    "by_game": {
      "cs2": {
        "graded": 3,
        "accuracy": 0.3333,
        "brier": 0.2971
      },
      "lol": {
        "graded": 0,
        "accuracy": null,
        "brier": null
      },
      "val": {
        "graded": 0,
        "accuracy": null,
        "brier": null
      }
    }
  },
  "training": {
    "cs2": {
      "n_train": 7,
      "trained": true,
      "shrinkage": 0.149,
      "l2_to_prior": 0.531,
      "in_sample_acc": 0.571
    },
    "lol": {
      "n_train": 0,
      "trained": false,
      "shrinkage": 0.0
    },
    "val": {
      "n_train": 0,
      "trained": false,
      "shrinkage": 0.0
    }
  },
  "calibration": {
    "cs2": [
      {
        "bucket": "0.50-0.62",
        "n": 5,
        "predicted": 0.562,
        "realized": 0.6
      },
      {
        "bucket": "0.62-0.75",
        "n": 2,
        "predicted": 0.688,
        "realized": 0.0
      }
    ],
    "lol": [],
    "val": []
  },
  "case_based": {
    "lol": {
      "accuracy": 0.6895,
      "note": "OE kNN, 702-game holdout (static)"
    },
    "cs2": {
      "n_cases": 296,
      "holdout_maps": 60,
      "k": 25,
      "accuracy": 0.4167,
      "brier": 0.2735
    },
    "val": {
      "n_cases": 770,
      "holdout_maps": 154,
      "k": 25,
      "accuracy": 0.5909,
      "brier": 0.236
    }
  },
  "slate": {
    "cs2": [
      {
        "match_id": "big-b8-2026-06-09",
        "event": "IEM Cologne 2026 Major",
        "team_a": "BIG",
        "team_b": "B8",
        "p_map_a": 0.3903,
        "p_a": 0.3381,
        "fmt": "BO3",
        "confidence": "lean",
        "scoreline": {
          "pick": "0-2",
          "a": 0,
          "b": 2,
          "p": 0.3717,
          "dist": [
            {
              "score": "0-2",
              "p": 0.3717
            },
            {
              "score": "1-2",
              "p": 0.2902
            },
            {
              "score": "2-1",
              "p": 0.1858
            },
            {
              "score": "2-0",
              "p": 0.1523
            }
          ]
        },
        "scheduled_at": "2026-06-09T17:00:00+00:00",
        "date": "2026-06-09",
        "features": {
          "rating_diff": -0.8938,
          "form_diff": -0.1,
          "map_diff": 0.0,
          "player_diff": -0.128,
          "h2h_diff": 0.0
        },
        "similar_matches": [
          {
            "date": "2026-05-11",
            "blue_team": "PARIVISION",
            "red_team": "Aurora Gaming",
            "winner": "Aurora Gaming",
            "winner_side": "red",
            "target": 0,
            "distance": 0.2519
          },
          {
            "date": "2026-06-09",
            "blue_team": "Monte",
            "red_team": "PaiN Gaming",
            "winner": "Monte",
            "winner_side": "blue",
            "target": 1,
            "distance": 0.2734
          },
          {
            "date": "2025-06-12",
            "blue_team": "Team Vitality",
            "red_team": "Legacy",
            "winner": "Legacy",
            "winner_side": "red",
            "target": 0,
            "distance": 0.309
          },
          {
            "date": "2025-06-14",
            "blue_team": "Natus Vincere",
            "red_team": "G2 Esports",
            "winner": "Natus Vincere",
            "winner_side": "blue",
            "target": 1,
            "distance": 0.5053
          },
          {
            "date": "2025-06-12",
            "blue_team": "Natus Vincere",
            "red_team": "Nemiga Gaming",
            "winner": "Natus Vincere",
            "winner_side": "blue",
            "target": 1,
            "distance": 0.553
          }
        ],
        "case_based": {
          "p_blue_knn": 0.48,
          "k": 25,
          "outcome_rate": "3/5",
          "note": "CS2 Elo/form/H2H kNN (k=25). Nearer = more similar on 4 derived features."
        }
      }
    ],
    "lol": [
      {
        "match_id": "anyoneslegend-bilibiligaming-2026-06-08",
        "event": "LPL 2026 Split 2 · Lower Bracket Semifinal",
        "team_a": "Anyone's Legend",
        "team_b": "Bilibili Gaming",
        "p_map_a": 0.56,
        "p_a": 0.5896,
        "fmt": "BO3",
        "confidence": "lean",
        "scoreline": {
          "pick": "2-0",
          "a": 2,
          "b": 0,
          "p": 0.3136,
          "dist": [
            {
              "score": "2-0",
              "p": 0.3136
            },
            {
              "score": "2-1",
              "p": 0.276
            },
            {
              "score": "1-2",
              "p": 0.2168
            },
            {
              "score": "0-2",
              "p": 0.1936
            }
          ]
        },
        "pick_source": "case_based",
        "scheduled_at": "2026-06-08T09:00:00+00:00",
        "date": "2026-06-08",
        "features": {
          "rating_diff": 0.0,
          "form_diff": 0.0,
          "map_diff": 0.0,
          "player_diff": 0.0,
          "h2h_diff": 0.0
        },
        "similar_matches": [
          {
            "gameid": "LOLTMNT05_132230",
            "date": "2025-05-21T19:20:37",
            "blue_team": "BBL Dark Passage",
            "red_team": "ULF Esports",
            "target": 0,
            "winner": "ULF Esports",
            "winner_side": "red",
            "distance": 0.6017
          },
          {
            "gameid": "LOLTMNT05_133187",
            "date": "2025-05-21T15:09:28",
            "blue_team": "BBL Dark Passage",
            "red_team": "ULF Esports",
            "target": 1,
            "winner": "BBL Dark Passage",
            "winner_side": "blue",
            "distance": 0.6486
          },
          {
            "gameid": "LOLTMNT03_292093",
            "date": "2025-08-27T08:04:11",
            "blue_team": "T1",
            "red_team": "Hanwha Life Esports",
            "target": 1,
            "winner": "T1",
            "winner_side": "blue",
            "distance": 0.7434
          },
          {
            "gameid": "LOLTMNT02_34511",
            "date": "2024-01-28T10:40:23",
            "blue_team": "Hanwha Life Esports",
            "red_team": "T1",
            "target": 0,
            "winner": "T1",
            "winner_side": "red",
            "distance": 0.7464
          },
          {
            "gameid": "LOLTMNT04_31429",
            "date": "2024-03-13T20:43:04",
            "blue_team": "RED Academy",
            "red_team": "FURIA Youth",
            "target": 1,
            "winner": "RED Academy",
            "winner_side": "blue",
            "distance": 0.7568
          }
        ],
        "case_based": {
          "p_blue_knn": 0.56,
          "k": 75,
          "outcome_rate": "3/5"
        }
      }
    ],
    "val": [
      {
        "match_id": "globalesports-fullsense-2026-06-09",
        "event": "VCT 2026 · Stage 2 Masters",
        "team_a": "Global Esports",
        "team_b": "FULL SENSE",
        "p_map_a": 0.3508,
        "p_a": 0.2828,
        "fmt": "BO3",
        "confidence": "moderate",
        "scoreline": {
          "pick": "0-2",
          "a": 0,
          "b": 2,
          "p": 0.4215,
          "dist": [
            {
              "score": "0-2",
              "p": 0.4215
            },
            {
              "score": "1-2",
              "p": 0.2957
            },
            {
              "score": "2-1",
              "p": 0.1598
            },
            {
              "score": "2-0",
              "p": 0.123
            }
          ]
        },
        "scheduled_at": "2026-06-09T17:20:00+00:00",
        "date": "2026-06-09",
        "features": {
          "rating_diff": -0.6242,
          "form_diff": -0.1,
          "map_diff": 0.0,
          "player_diff": -0.125,
          "h2h_diff": -1.0
        },
        "similar_matches": [
          {
            "date": "2026-02-05",
            "blue_team": "Team Secret",
            "red_team": "ZETA DIVISION",
            "winner": "ZETA DIVISION",
            "winner_side": "red",
            "target": 0,
            "distance": 0.3497
          },
          {
            "date": "2026-05-11",
            "blue_team": "Sentinels",
            "red_team": "NRG",
            "winner": "NRG",
            "winner_side": "red",
            "target": 0,
            "distance": 0.4042
          },
          {
            "date": "2025-07-27",
            "blue_team": "Cloud9",
            "red_team": "Evil Geniuses",
            "winner": "Cloud9",
            "winner_side": "blue",
            "target": 1,
            "distance": 0.446
          },
          {
            "date": "2025-03-29",
            "blue_team": "Dragon Ranger Gaming",
            "red_team": "EDward Gaming",
            "winner": "EDward Gaming",
            "winner_side": "red",
            "target": 0,
            "distance": 0.4472
          },
          {
            "date": "2025-02-24",
            "blue_team": "T1",
            "red_team": "DRX",
            "winner": "T1",
            "winner_side": "blue",
            "target": 1,
            "distance": 0.4735
          }
        ],
        "case_based": {
          "p_blue_knn": 0.4,
          "k": 25,
          "outcome_rate": "2/5",
          "note": "Valorant Elo/form/H2H kNN (k=25). Nearer = more similar on 4 derived features."
        }
      },
      {
        "match_id": "viewmatchdetails-previous-2026-06-10",
        "event": "VCT 2026 · Stage 2 Masters",
        "team_a": "View match details",
        "team_b": "Previous",
        "p_map_a": 0.5,
        "p_a": 0.5,
        "fmt": "BO3",
        "confidence": "coin-flip",
        "scoreline": {
          "pick": "2-0",
          "a": 2,
          "b": 0,
          "p": 0.25,
          "dist": [
            {
              "score": "2-0",
              "p": 0.25
            },
            {
              "score": "2-1",
              "p": 0.25
            },
            {
              "score": "0-2",
              "p": 0.25
            },
            {
              "score": "1-2",
              "p": 0.25
            }
          ]
        },
        "scheduled_at": "2026-06-10T17:00:00+00:00",
        "date": "2026-06-10",
        "features": {
          "rating_diff": 0.0,
          "form_diff": 0.0,
          "map_diff": 0.0,
          "player_diff": 0.0,
          "h2h_diff": 0.0
        }
      }
    ]
  },
  "results": {
    "cs2": [],
    "lol": [],
    "val": []
  },
  "notes": [
    "Tier-1 events only (CS2 LAN; LoL LPL/LCK/etc.; Valorant VCT).",
    "Auto-fetched from Liquipedia daily at 00:00 Beijing (16:00 UTC).",
    "Rolling 1-year window; older predictions auto-purged.",
    "Model self-trains daily on graded results, anchored to the prior.",
    "p_a = probability the first-listed team wins the series.",
    "Case-based 'similar matches' are transparency, not the pick: the displayed win% is the calibrated model. LoL kNN ~69% out-of-sample; CS2/Valorant kNN provisional (small Liquipedia corpus) - see case_based."
  ]
}